apit212/Apit212.py
apit212/Constant.py
apit212/Instrument.py
apit212/__init__.py
apit212/tempCodeRunnerFile.py
apit212-3.0.1.dist-info/LICENSE
apit212-3.0.1.dist-info/METADATA
apit212-3.0.1.dist-info/WHEEL
apit212-3.0.1.dist-info/top_level.txt
apit212-3.0.1.dist-info/RECORD
