Metadata-Version: 2.1
Name: apit212
Version: 3.0.1
Summary: Unofficial trading212 API
Home-page: https://github.com/Flock92/aPit212
Author: Flock92
Author-email: Flock92 <stuwe_3000@outlook.com>
Maintainer-email: Flock92 <stuwe_3000@outlook.com>
License: MIT
Project-URL: Homepage, https://github.com/Flock92/apit212
Project-URL: Bug Tracker, https://github.com/Flock92/apit212/issues
Keywords: trading,trading212,api,trade,flock92
Classifier: Programming Language :: Python :: 3
Classifier: License :: OSI Approved :: MIT License
Classifier: Operating System :: OS Independent
Classifier: Development Status :: 4 - Beta
Requires: requests
Requires: selenium
Requires-Python: >=3.9
License-File: LICENSE
Requires-Dist: selenium >4.7.2
Requires-Dist: requests >2.28.2
